{"cameraMode":{"drawMode":0,"name":"Shaded","section":"Shading Mode"},"sceneLighting":true,"audioPlay":false,"sceneViewState":{"m_AlwaysRefresh":false,"showFog":true,"showSkybox":true,"showFlares":true,"showImageEffects":true,"showParticleSystems":true,"showVisualEffectGraphs":true,"m_FxEnabled":true},"in2DMode":false,"pivot":{"x":35.849849700927737,"y":2.8851966857910158,"z":30.018112182617189},"rotation":{"x":-0.2235870510339737,"y":0.3002992272377014,"z":-0.07263248413801193,"w":-0.9244210124015808},"size":53.16341781616211,"orthographic":false}